futeamigos/__init__.py
futeamigos-0.0.3.dist-info/LICENSE
futeamigos-0.0.3.dist-info/METADATA
futeamigos-0.0.3.dist-info/WHEEL
futeamigos-0.0.3.dist-info/top_level.txt
futeamigos-0.0.3.dist-info/RECORD
