Metadata-Version: 2.1
Name: futeamigos
Version: 0.0.3
Summary: Package for Reinforcement Learning in MO436-UNICAMP
Home-page: https://gitlab.com/patrickctrf/mo436-project-01
Author: patrickctrf
Author-email: patrickctrf@gmail.com
License: UNKNOWN
Platform: UNKNOWN
Classifier: Programming Language :: Python :: 3
Classifier: License :: OSI Approved :: MIT License
Classifier: Operating System :: OS Independent
Requires-Python: >=3.6
